src/__init__.py
secdb-0.1.dist-info/METADATA
secdb-0.1.dist-info/WHEEL
secdb-0.1.dist-info/top_level.txt
secdb-0.1.dist-info/RECORD
